yrwatertemperatures/__init__.py
yrwatertemperatures/py.typed
yrwatertemperatures-1.0.0.dist-info/licenses/LICENSE
yrwatertemperatures-1.0.0.dist-info/METADATA
yrwatertemperatures-1.0.0.dist-info/WHEEL
yrwatertemperatures-1.0.0.dist-info/top_level.txt
yrwatertemperatures-1.0.0.dist-info/RECORD
