Metadata-Version: 2.4
Name: yrwatertemperatures
Version: 1.0.0
Summary: A Python client to fetch water temperatures in Norway from YR.no.
Author-email: Jørn Pettersen <joern.pettersen@gmail.com>
License: MIT
Project-URL: Homepage, https://github.com/jornpe/yr-norwegian-water-temperatures
Project-URL: Documentation, https://github.com/jornpe/yr-norwegian-water-temperatures#readme
Project-URL: Repository, https://github.com/jornpe/yr-norwegian-water-temperatures.git
Project-URL: Bug Tracker, https://github.com/jornpe/yr-norwegian-water-temperatures/issues
Project-URL: Changelog, https://github.com/jornpe/yr-norwegian-water-temperatures/releases
Keywords: norway,water,temperature,yr,weather,api
Classifier: Development Status :: 5 - Production/Stable
Classifier: Intended Audience :: Developers
Classifier: Natural Language :: English
Classifier: License :: OSI Approved :: MIT License
Classifier: Operating System :: OS Independent
Classifier: Programming Language :: Python
Classifier: Programming Language :: Python :: 3
Classifier: Programming Language :: Python :: 3.12
Classifier: Programming Language :: Python :: 3.13
Classifier: Programming Language :: Python :: 3 :: Only
Classifier: Topic :: Software Development :: Libraries :: Python Modules
Classifier: Topic :: Scientific/Engineering :: Atmospheric Science
Classifier: Typing :: Typed
Requires-Python: >=3.12
License-File: LICENSE
Requires-Dist: requests>=2.20.0
Requires-Dist: aiohttp>=3.8.0
Provides-Extra: test
Requires-Dist: pytest>=7.0.0; extra == "test"
Requires-Dist: pytest-asyncio>=0.21.0; extra == "test"
Requires-Dist: aioresponses>=0.7.4; extra == "test"
Provides-Extra: dev
Requires-Dist: pytest>=7.0.0; extra == "dev"
Requires-Dist: pytest-asyncio>=0.21.0; extra == "dev"
Requires-Dist: aioresponses>=0.7.4; extra == "dev"
Requires-Dist: black>=22.0.0; extra == "dev"
Requires-Dist: isort>=5.10.0; extra == "dev"
Requires-Dist: mypy>=1.0.0; extra == "dev"
Requires-Dist: pre-commit>=2.20.0; extra == "dev"
Dynamic: license-file
